setup.py
rwtfoms.egg-info/PKG-INFO
rwtfoms.egg-info/SOURCES.txt
rwtfoms.egg-info/dependency_links.txt
rwtfoms.egg-info/requires.txt
rwtfoms.egg-info/top_level.txt
rwtforms/__init__.py