Metadata-Version: 1.0
Name: rwtfoms
Version: 0.0.1
Summary: WTForms support for Rueckenwind
Home-page: UNKNOWN
Author: Florian Ludwig
Author-email: f.ludwig@greyrook.com
License: UNKNOWN
Platform: UNKNOWN
